ImgurPy/Account.py
ImgurPy/Album.py
ImgurPy/Authenticate.py
ImgurPy/Image.py
ImgurPy/__init__.py
ImgurPy/core.py
ImgurPy/imgurPy.py
imgurPy-0.0.1b0.dist-info/LICENSE
imgurPy-0.0.1b0.dist-info/METADATA
imgurPy-0.0.1b0.dist-info/WHEEL
imgurPy-0.0.1b0.dist-info/entry_points.txt
imgurPy-0.0.1b0.dist-info/top_level.txt
imgurPy-0.0.1b0.dist-info/RECORD
